{"stem":"badisch","instances":[{"docId":"1061","docUri":"1061.html","score":3,"contexts":[{"form":"Badische","weight":"1","pos":526,"context":"...20. 4. 1537 (Wien, HHStA, RHR <mark>Badische<\/mark> Akten, Judicialia (Prozessakten) 7\/8). Testamentarische Regelungen...","fid":"letterContent"},{"form":"Badische","weight":"1","pos":546,"context":"...6. 1532, s. Wien, HHStA, RHR <mark>Badische<\/mark> Akten, Confirmationes privilegiorum 1\/23). Übrigens hatte zu dieser...","fid":"letterContent"},{"form":"Badische","weight":"1","pos":565,"context":"...Beschwerde erhoben hatten (Wien, HHStA, RHR <mark>Badische<\/mark> Akten, Judicialia (Prozessakten) 7\/7). ","fid":"letterContent"}]}]}