{"stem":"gerechtfertigt","instances":[{"docId":"A026","docUri":"A026.html","score":1,"contexts":[{"form":"gerechtfertigt","weight":"1","pos":3038,"context":"25] Wie <mark>gerechtfertigt<\/mark> F’s Klage über den Mangel an Verschwiegenheit bei den...","fid":"letterContent"}]},{"docId":"1067","docUri":"1067.html","score":1,"contexts":[{"form":"gerechtfertigt","weight":"1","pos":4150,"context":"...von Franz I. erhobenen Ansprüche dort in keiner Weise <mark>gerechtfertigt<\/mark> seien und dass die Auseinandersetzung um Italien den Türken...","fid":"letterContent"}]}]}